pyeloqua
