Metadata-Version: 1.0
Name: pyeloqua
Version: 0.5.10
Summary: Python wrapper functions for Eloqua APIs
Home-page: https://github.com/colemanja91/pyeloqua
Author: Jeremiah Coleman
Author-email: colemanja91@gmail.com
License: MIT
Keywords: eloqua marketing automation api bulk
Platform: UNKNOWN
